efcCache/Interface.py
efcCache/Manager.py
efcCache/__init__.py
efcCache/providers/FileCache.py
efcCache/providers/MySQLCache.py
efcCache/providers/PostgreSQLCache.py
efcCache/providers/RedisCache.py
efcCache/providers/SQLiteCache.py
efcCache/providers/__init__.py
efcCache-0.0.4.dist-info/METADATA
efcCache-0.0.4.dist-info/WHEEL
efcCache-0.0.4.dist-info/top_level.txt
efcCache-0.0.4.dist-info/RECORD
