Metadata-Version: 2.1
Name: efcCache
Version: 0.0.4
Summary: A file storage management package supporting various providers like S3, OSS, and Qiniu.
Home-page: https://github.com/duolabmeng6/efcCache
Author: duolabmeng6
Author-email: 1715109585@qq.com
Keywords: efcCache
Classifier: Programming Language :: Python :: 3
Classifier: License :: OSI Approved :: MIT License
Classifier: Operating System :: OS Independent
Requires-Python: >=3.6
